jjk_sheet/__init__.py
jjk_sheet/jjk_sheet.py
jjk_sheet-1.1.3.dist-info/LICENSE
jjk_sheet-1.1.3.dist-info/METADATA
jjk_sheet-1.1.3.dist-info/WHEEL
jjk_sheet-1.1.3.dist-info/top_level.txt
jjk_sheet-1.1.3.dist-info/RECORD
