Metadata-Version: 2.1
Name: jjk-sheet
Version: 1.1.3
Summary: Uma biblioteca para a obtenção de dados de uma ficha do rpg Feiticeiros e Maldições.
Author-email: H0ruh3 <jorgemenezesaf@gmail.com>
License: MIT License
Keywords: jjk_sheet,rpg,jujutsu,kaisen,ficha
Classifier: Development Status :: 5 - Production/Stable
Classifier: Intended Audience :: Developers
Classifier: License :: OSI Approved :: MIT License
Classifier: Natural Language :: Portuguese (Brazilian)
Classifier: Operating System :: OS Independent
Classifier: Programming Language :: Python :: 3.11
Classifier: Topic :: Games/Entertainment
Classifier: Topic :: Games/Entertainment :: Role-Playing
Requires-Python: >=3.10.7
License-File: LICENSE
Requires-Dist: gspread
Requires-Dist: google-api-python-client
Requires-Dist: google-auth-httplib2
Requires-Dist: google-auth-oauthlib
